filetransfer/__init__.py
filetransfer/__main__.py
filetransfer/base.py
filetransfer/config.py
filetransfer/const.py
filetransfer/exceptions.py
filetransfer/ftp.py
filetransfer/job.py
filetransfer/local.py
filetransfer/loghandler.py
filetransfer/mail.py
filetransfer/sftp.py
filetransfer/utils.py
filetransfer/data/__init__.py
filetransfer/data/app_config_spec.ini
filetransfer/data/default.mail
filetransfer/data/host_config_spec.ini
filetransfer/data/job_config_spec.ini
FileTransfer-0.11.0.dist-info/LICENSE.txt
FileTransfer-0.11.0.dist-info/METADATA
FileTransfer-0.11.0.dist-info/WHEEL
FileTransfer-0.11.0.dist-info/entry_points.txt
FileTransfer-0.11.0.dist-info/top_level.txt
FileTransfer-0.11.0.dist-info/RECORD
