Metadata-Version: 2.1
Name: FileTransfer
Version: 0.11.0
Summary: Application and library for file transfer.
Home-page: https://andreas19.github.io/FileTransfer/
Author: Andreas Suhre
Author-email: andreas19@posteo.eu
License: BSD-3-Clause
Project-URL: Source code, https://github.com/andreas19/FileTransfer/
Keywords: files,filetransfer,ftp,ftps,sftp,transfer
Platform: UNKNOWN
Classifier: Development Status :: 4 - Beta
Classifier: Intended Audience :: Developers
Classifier: Intended Audience :: System Administrators
Classifier: License :: OSI Approved :: BSD License
Classifier: Natural Language :: English
Classifier: Operating System :: OS Independent
Classifier: Programming Language :: Python :: 3
Classifier: Programming Language :: Python :: 3.6
Classifier: Programming Language :: Python :: 3.7
Classifier: Programming Language :: Python :: 3.8
Classifier: Programming Language :: Python :: 3.9
Classifier: Topic :: Internet :: File Transfer Protocol (FTP)
Classifier: Topic :: Software Development :: Libraries
Requires-Python: >=3.6
License-File: LICENSE.txt
Requires-Dist: easimpconf (>=0.2.2)
Requires-Dist: ftputil (>=4)
Requires-Dist: paramiko (~=2.7)
Requires-Dist: salmagundi (>=0.15.0)
Requires-Dist: importlib-resources (>=1.0.2) ; python_version < "3.7"
Requires-Dist: dataclasses (>=0.7) ; python_version < "3.7"
